org_dist_cdk/__init__.py
org_dist_cdk/apigateway.py
org_dist_cdk/multilambda.py
org_ds_cdk/__init__.py
org_ds_cdk/apigateway copy.py
org_ds_cdk/apigateway.py
org_ds_cdk/multilambda copy.py
org_ds_cdk/multilambda.py
org_ds_cdk/utils.py
org_ds_cdk/vpc.py
org_ds_cdk-0.1.7.dist-info/METADATA
org_ds_cdk-0.1.7.dist-info/WHEEL
org_ds_cdk-0.1.7.dist-info/top_level.txt
org_ds_cdk-0.1.7.dist-info/RECORD
