Metadata-Version: 2.1
Name: org-ds-cdk
Version: 0.1.7
Summary: DS Organization CDK Constructs
Home-page: UNKNOWN
License: UNKNOWN
Platform: UNKNOWN
Requires-Dist: aws-cdk-lib ==2.142.0
Requires-Dist: constructs >=10.0.0
